AUTHORS.rst
CONTRIBUTING.rst
LICENSE
MANIFEST.in
README.rst
requirements.txt
setup.cfg
setup.py
versioneer.py
autocorr/__init__.py
autocorr/_version.py
autocorr/fftautocorr.py
autocorr/multitau.py
autocorr.egg-info/PKG-INFO
autocorr.egg-info/SOURCES.txt
autocorr.egg-info/dependency_links.txt
autocorr.egg-info/entry_points.txt
autocorr.egg-info/requires.txt
autocorr.egg-info/top_level.txt
autocorr/tests/__init__.py
autocorr/tests/conftest.py
autocorr/tests/test_multitau.py
docs/Makefile
docs/make.bat
docs/source/conf.py
docs/source/index.rst
docs/source/installation.rst
docs/source/release-history.rst
docs/source/usage.rst
src/cpu_multitau.cpp
src/fftautocorr.cpp
src/pyMultiTau.cpp