Metadata-Version: 1.2
Name: autocorr
Version: 0.0.1
Summary: Library for XPCS and image autocorrelation in general
Home-page: https://github.com/scikit-beam/autocorr
Author: BES Data Solutions Pilot
Author-email: dallan@bnl.gov
License: BSD (3-clause)
Platform: UNKNOWN
Classifier: Development Status :: 2 - Pre-Alpha
Classifier: Natural Language :: English
Classifier: Programming Language :: Python :: 3
Requires-Python: >=3.6
